qaseio/__init__.py
qaseio/api_client.py
qaseio/api_response.py
qaseio/configuration.py
qaseio/exceptions.py
qaseio/py.typed
qaseio/rest.py
qaseio/api/__init__.py
qaseio/api/attachments_api.py
qaseio/api/authors_api.py
qaseio/api/cases_api.py
qaseio/api/configurations_api.py
qaseio/api/custom_fields_api.py
qaseio/api/defects_api.py
qaseio/api/environments_api.py
qaseio/api/milestones_api.py
qaseio/api/plans_api.py
qaseio/api/projects_api.py
qaseio/api/results_api.py
qaseio/api/runs_api.py
qaseio/api/search_api.py
qaseio/api/shared_steps_api.py
qaseio/api/suites_api.py
qaseio/api/system_fields_api.py
qaseio/models/__init__.py
qaseio/models/attachment.py
qaseio/models/attachment_get.py
qaseio/models/attachment_hash.py
qaseio/models/attachment_list_response.py
qaseio/models/attachment_list_response_all_of_result.py
qaseio/models/attachment_response.py
qaseio/models/attachment_uploads_response.py
qaseio/models/attachmentupload.py
qaseio/models/author.py
qaseio/models/author_list_response.py
qaseio/models/author_list_response_all_of_result.py
qaseio/models/author_response.py
qaseio/models/base_response.py
qaseio/models/bulk200_response.py
qaseio/models/bulk200_response_all_of_result.py
qaseio/models/configuration.py
qaseio/models/configuration_create.py
qaseio/models/configuration_group.py
qaseio/models/configuration_group_create.py
qaseio/models/configuration_list_response.py
qaseio/models/configuration_list_response_all_of_result.py
qaseio/models/custom_field.py
qaseio/models/custom_field_create.py
qaseio/models/custom_field_create_value_inner.py
qaseio/models/custom_field_list_response.py
qaseio/models/custom_field_response.py
qaseio/models/custom_field_update.py
qaseio/models/custom_field_value.py
qaseio/models/custom_fields_response.py
qaseio/models/custom_fields_response_all_of_result.py
qaseio/models/defect.py
qaseio/models/defect_create.py
qaseio/models/defect_list_response.py
qaseio/models/defect_list_response_all_of_result.py
qaseio/models/defect_query.py
qaseio-4.0.2.dist-info/LICENSE.txt
qaseio-4.0.2.dist-info/METADATA
qaseio-4.0.2.dist-info/WHEEL
qaseio-4.0.2.dist-info/top_level.txt
qaseio-4.0.2.dist-info/RECORD
