Metadata-Version: 2.1
Name: qaseio
Version: 4.0.2
Summary: Qase TestOps API client for Python
Author-email: Qase Team <support@qase.io>
Project-URL: Homepage, https://github.com/qase-tms/qase-python
Keywords: OpenAPI,OpenAPI-Generator,Qase.io TestOps API
Classifier: Development Status :: 5 - Production/Stable
Classifier: Programming Language :: Python :: 3.7
Classifier: Programming Language :: Python :: 3.8
Classifier: Programming Language :: Python :: 3.9
Classifier: Programming Language :: Python :: 3.10
Classifier: Programming Language :: Python :: 3.11
Classifier: Typing :: Typed
Requires-Python: >=3.7
License-File: LICENSE.txt
Requires-Dist: urllib3 <2.1.0,>=1.25.3
Requires-Dist: python-dateutil
Requires-Dist: pydantic >=2
Requires-Dist: typing-extensions >=4.7.1
